{ "frames": [
   {
    "filename": "desk-type-a-0",
    "frame": { "x": 0, "y": 0, "w": 64, "h": 64 },
    "rotated": false,
    "trimmed": false,
    "spriteSourceSize": { "x": 0, "y": 0, "w": 64, "h": 64 },
    "sourceSize": { "w": 64, "h": 64 },
    "duration": 100
   },
   {
    "filename": "desk-type-a-1",
    "frame": { "x": 64, "y": 0, "w": 64, "h": 64 },
    "rotated": false,
    "trimmed": false,
    "spriteSourceSize": { "x": 0, "y": 0, "w": 64, "h": 64 },
    "sourceSize": { "w": 64, "h": 64 },
    "duration": 100
   },
   {
    "filename": "desk-type-b-0",
    "frame": { "x": 128, "y": 0, "w": 64, "h": 64 },
    "rotated": false,
    "trimmed": false,
    "spriteSourceSize": { "x": 0, "y": 0, "w": 64, "h": 64 },
    "sourceSize": { "w": 64, "h": 64 },
    "duration": 100
   },
   {
    "filename": "desk-type-b-1",
    "frame": { "x": 192, "y": 0, "w": 64, "h": 64 },
    "rotated": false,
    "trimmed": false,
    "spriteSourceSize": { "x": 0, "y": 0, "w": 64, "h": 64 },
    "sourceSize": { "w": 64, "h": 64 },
    "duration": 100
   },
   {
    "filename": "edit-0",
    "frame": { "x": 256, "y": 0, "w": 64, "h": 64 },
    "rotated": false,
    "trimmed": false,
    "spriteSourceSize": { "x": 0, "y": 0, "w": 64, "h": 64 },
    "sourceSize": { "w": 64, "h": 64 },
    "duration": 100
   }
 ],
 "meta": {
  "app": "https://www.aseprite.org/",
  "version": "1.2.32-x64",
  "image": "office.png",
  "format": "RGBA8888",
  "size": { "w": 320, "h": 64 },
  "scale": "1",
  "frameTags": [
   { "name": "desk-type-a", "from": 0, "to": 1, "direction": "forward" },
   { "name": "desk-type-b", "from": 2, "to": 3, "direction": "forward" },
   { "name": "edit", "from": 4, "to": 4, "direction": "forward" }
  ],
  "layers": [
   { "name": "Layer 1", "opacity": 255, "blendMode": "normal" }
  ],
  "slices": [
  ]
 }
}
